{
  "_version": "1.1.0",
  "resources": [
    {
      "name": ".theming",
      "theme": "sap_hcb"
    },
    {
      "name": "ChartContainer.css",
      "theme": "sap_hcb"
    },
    {
      "name": "DateRangeScroller.css",
      "theme": "sap_hcb"
    },
    {
      "name": "FacetOverview.css",
      "theme": "sap_hcb"
    },
    {
      "name": "FeedTile.css",
      "theme": "sap_hcb"
    },
    {
      "name": "HeaderContainer.css",
      "theme": "sap_hcb"
    },
    {
      "name": "KpiTile.css",
      "theme": "sap_hcb"
    },
    {
      "name": "LinkActionSheet.css",
      "theme": "sap_hcb"
    },
    {
      "name": "NoteTaker.css",
      "theme": "sap_hcb"
    },
    {
      "name": "NoteTakerCard.css",
      "theme": "sap_hcb"
    },
    {
      "name": "NoteTakerFeeder.css",
      "theme": "sap_hcb"
    },
    {
      "name": "ProcessFlow.css",
      "theme": "sap_hcb"
    },
    {
      "name": "ProcessFlowConnection.css",
      "theme": "sap_hcb"
    },
    {
      "name": "ProcessFlowConnectionLabel.css",
      "theme": "sap_hcb"
    },
    {
      "name": "ProcessFlowLaneHeader.css",
      "theme": "sap_hcb"
    },
    {
      "name": "ProcessFlowNode.css",
      "theme": "sap_hcb"
    },
    {
      "name": "TargetFilter.css",
      "theme": "sap_hcb"
    },
    {
      "name": "ThingCollection.css",
      "theme": "sap_hcb"
    },
    {
      "name": "ThreePanelThingViewer.css",
      "theme": "sap_hcb"
    },
    {
      "name": "TimelineItem.css",
      "theme": "sap_hcb"
    },
    {
      "name": "UnifiedThingGroup.css",
      "theme": "sap_hcb"
    },
    {
      "name": "UnifiedThingInspector.css",
      "theme": "sap_hcb"
    },
    {
      "name": "VerticalNavigationBar.css",
      "theme": "sap_hcb"
    },
    {
      "name": "ViewRepeater.css",
      "theme": "sap_hcb"
    },
    {
      "name": "img-RTL/arrow_left.png",
      "theme": "sap_hcb"
    },
    {
      "name": "img-RTL/arrow_left_hover.png",
      "theme": "sap_hcb"
    },
    {
      "name": "img-RTL/arrow_right.png",
      "theme": "sap_hcb"
    },
    {
      "name": "img-RTL/arrow_right_hover.png",
      "theme": "sap_hcb"
    },
    {
      "name": "img-RTL/attachment_16.png",
      "theme": "sap_hcb"
    },
    {
      "name": "img-RTL/attachment_24.png",
      "theme": "sap_hcb"
    },
    {
      "name": "img-RTL/btn_actions_hover.png",
      "theme": "sap_hcb"
    },
    {
      "name": "img-RTL/btn_actions_regular.png",
      "theme": "sap_hcb"
    },
    {
      "name": "img-RTL/btn_nav_left_a.png",
      "theme": "sap_hcb"
    },
    {
      "name": "img-RTL/btn_nav_left_p.png",
      "theme": "sap_hcb"
    },
    {
      "name": "img-RTL/btn_nav_right_a.png",
      "theme": "sap_hcb"
    },
    {
      "name": "img-RTL/btn_nav_right_p.png",
      "theme": "sap_hcb"
    },
    {
      "name": "img-RTL/bubble.png",
      "theme": "sap_hcb"
    },
    {
      "name": "img-RTL/bubble_1.png",
      "theme": "sap_hcb"
    },
    {
      "name": "img-RTL/decline_16.png",
      "theme": "sap_hcb"
    },
    {
      "name": "img-RTL/delete_16.png",
      "theme": "sap_hcb"
    },
    {
      "name": "img-RTL/edit_24.png",
      "theme": "sap_hcb"
    },
    {
      "name": "img-RTL/edit_grey_24.png",
      "theme": "sap_hcb"
    },
    {
      "name": "img-RTL/home_24.png",
      "theme": "sap_hcb"
    },
    {
      "name": "img-RTL/img_bg.png",
      "theme": "sap_hcb"
    },
    {
      "name": "img-RTL/img_bg_ti.png",
      "theme": "sap_hcb"
    },
    {
      "name": "img-RTL/search_24.png",
      "theme": "sap_hcb"
    },
    {
      "name": "img-RTL/stripes.png",
      "theme": "sap_hcb"
    },
    {
      "name": "img-RTL/tag_24.png",
      "theme": "sap_hcb"
    },
    {
      "name": "img-RTL/thumbDown_24.png",
      "theme": "sap_hcb"
    },
    {
      "name": "img-RTL/thumbUp_24.png",
      "theme": "sap_hcb"
    },
    {
      "name": "img/arrow_left.png",
      "theme": "sap_hcb"
    },
    {
      "name": "img/arrow_left_hover.png",
      "theme": "sap_hcb"
    },
    {
      "name": "img/arrow_right.png",
      "theme": "sap_hcb"
    },
    {
      "name": "img/arrow_right_hover.png",
      "theme": "sap_hcb"
    },
    {
      "name": "img/attachment_16.png",
      "theme": "sap_hcb"
    },
    {
      "name": "img/attachment_24.png",
      "theme": "sap_hcb"
    },
    {
      "name": "img/btn_actions_hover.png",
      "theme": "sap_hcb"
    },
    {
      "name": "img/btn_actions_regular.png",
      "theme": "sap_hcb"
    },
    {
      "name": "img/btn_nav_left_a.png",
      "theme": "sap_hcb"
    },
    {
      "name": "img/btn_nav_left_p.png",
      "theme": "sap_hcb"
    },
    {
      "name": "img/btn_nav_right_a.png",
      "theme": "sap_hcb"
    },
    {
      "name": "img/btn_nav_right_p.png",
      "theme": "sap_hcb"
    },
    {
      "name": "img/bubble.png",
      "theme": "sap_hcb"
    },
    {
      "name": "img/bubble_1.png",
      "theme": "sap_hcb"
    },
    {
      "name": "img/decline_16.png",
      "theme": "sap_hcb"
    },
    {
      "name": "img/delete_16.png",
      "theme": "sap_hcb"
    },
    {
      "name": "img/edit_24.png",
      "theme": "sap_hcb"
    },
    {
      "name": "img/edit_grey_24.png",
      "theme": "sap_hcb"
    },
    {
      "name": "img/home_24.png",
      "theme": "sap_hcb"
    },
    {
      "name": "img/img_bg.png",
      "theme": "sap_hcb"
    },
    {
      "name": "img/img_bg_ti.png",
      "theme": "sap_hcb"
    },
    {
      "name": "img/search_24.png",
      "theme": "sap_hcb"
    },
    {
      "name": "img/stripes.png",
      "theme": "sap_hcb"
    },
    {
      "name": "img/tag_24.png",
      "theme": "sap_hcb"
    },
    {
      "name": "img/thumbDown_24.png",
      "theme": "sap_hcb"
    },
    {
      "name": "img/thumbUp_24.png",
      "theme": "sap_hcb"
    },
    {
      "name": "library-RTL-dbg.css",
      "isDebug": true,
      "theme": "sap_hcb"
    },
    {
      "name": "library-RTL.css",
      "theme": "sap_hcb"
    },
    {
      "name": "library-dbg.css",
      "isDebug": true,
      "theme": "sap_hcb"
    },
    {
      "name": "library-parameters.json",
      "theme": "sap_hcb"
    },
    {
      "name": "library.css",
      "theme": "sap_hcb"
    },
    {
      "name": "library.less",
      "designtime": true,
      "theme": "sap_hcb"
    },
    {
      "name": "library.source.less",
      "designtime": true,
      "theme": "sap_hcb"
    },
    {
      "name": "shared.css",
      "theme": "sap_hcb"
    }
  ]
}